Django_sign_up/__init__.py
Django_sign_up/url.py
Django_sign_up/views.py
Django_sign_up-0.0.4.dist-info/DESCRIPTION.rst
Django_sign_up-0.0.4.dist-info/METADATA
Django_sign_up-0.0.4.dist-info/RECORD
Django_sign_up-0.0.4.dist-info/WHEEL
Django_sign_up-0.0.4.dist-info/metadata.json
Django_sign_up-0.0.4.dist-info/top_level.txt
