Metadata-Version: 2.0
Name: Django-sign-up
Version: 0.0.4
Summary: DJango sign up
Home-page: UNKNOWN
Author: harish r
Author-email: harish.r@imailt.com
License: UNKNOWN
Platform: UNKNOWN
Classifier: Programming Language :: Python :: 3
Classifier: License :: OSI Approved :: MIT License
Classifier: Operating System :: OS Independent
